fk12306/__init__.py
fk12306/__version__.py
fk12306/config.py
fk12306/exceptions.py
fk12306/glovar.py
fk12306/request.py
fk12306/train.py
fk12306/utils.py
fk12306/data/cdn.txt
fk12306/data/proxies.txt
fk12306/data/stations.txt
fk12306-0.1.1.dist-info/LICENSE
fk12306-0.1.1.dist-info/METADATA
fk12306-0.1.1.dist-info/WHEEL
fk12306-0.1.1.dist-info/entry_points.txt
fk12306-0.1.1.dist-info/top_level.txt
fk12306-0.1.1.dist-info/RECORD
