Metadata-Version: 2.1
Name: fk12306
Version: 0.1.1
Summary: 12306查票助手，一键查询沿途所有站点，先上车后补票，暂不支持抢票
Home-page: https://github.com/0xHJK/fk12306
Author: HJK
Author-email: HJKdev@gmail.com
License: MIT License
Platform: UNKNOWN
Classifier: Development Status :: 4 - Beta
Classifier: Environment :: Console
Classifier: Intended Audience :: Developers
Classifier: Intended Audience :: End Users/Desktop
Classifier: License :: OSI Approved :: MIT License
Classifier: Operating System :: OS Independent
Classifier: Programming Language :: Python
Classifier: Programming Language :: Python :: 3
Classifier: Programming Language :: Python :: 3 :: Only
Classifier: Programming Language :: Python :: 3.5
Classifier: Programming Language :: Python :: 3.6
Classifier: Programming Language :: Python :: 3.7
Classifier: Topic :: Internet
Classifier: Topic :: Internet :: WWW/HTTP
Classifier: Topic :: Utilities
Requires-Dist: requests
Requires-Dist: click
Requires-Dist: prettytable
